wraptext-0.1.0b1.dist-info/METADATA
wraptext-0.1.0b1.dist-info/WHEEL
wraptext-0.1.0b1.dist-info/license_files/LICENSE.md
wraptext/__init__.py
wraptext/wraptext.cpython-38-x86_64-linux-gnu.so
wraptext-0.1.0b1.dist-info/RECORD
